[{"id":1,"name":"Творог","calories":232,"weight":100},{"id":2,"name":"Перепелка запеченная","calories":"207","weight":"100"},{"id":3,"name":"Салат овощной","calories":"34.8","weight":"100"},{"id":4,"name":"Гречневая каша","calories":"90","weight":"100"},{"id":5,"name":"Яйцо вареное","calories":"158","weight":"100"},{"id":6,"name":"Свинные отбивные (жаренные)","calories":"279","weight":"100"},{"id":7,"name":"Компот","calories":"60","weight":"100"},{"id":8,"name":"Куриная грудка на пару","calories":"113","weight":"100"},{"id":9,"name":"Морковь","calories":"32","weight":"100"}]